scope3ai/__init__.py
scope3ai/base_tracer.py
scope3ai/constants.py
scope3ai/lib.py
scope3ai/worker.py
scope3ai/wrapper.py
scope3ai/api/__init__.py
scope3ai/api/client.py
scope3ai/api/commandsgen.py
scope3ai/api/defaults.py
scope3ai/api/tracer.py
scope3ai/api/types.py
scope3ai/api/typesgen.py
scope3ai/response_interceptor/aiohttp_interceptor.py
scope3ai/response_interceptor/instrument.py
scope3ai/response_interceptor/requests_interceptor.py
scope3ai/tracers/anthropic/chat.py
scope3ai/tracers/anthropic/instrument.py
scope3ai/tracers/cohere/chat.py
scope3ai/tracers/cohere/chat_v2.py
scope3ai/tracers/cohere/instrument.py
scope3ai/tracers/huggingface/chat.py
scope3ai/tracers/huggingface/image_to_image.py
scope3ai/tracers/huggingface/instrument.py
scope3ai/tracers/huggingface/speech_to_text.py
scope3ai/tracers/huggingface/text_to_image.py
scope3ai/tracers/huggingface/text_to_speech.py
scope3ai/tracers/huggingface/translation.py
scope3ai/tracers/huggingface/utils.py
scope3ai/tracers/huggingface/vision/image_classification.py
scope3ai/tracers/huggingface/vision/image_segmentation.py
scope3ai/tracers/huggingface/vision/object_detection.py
scope3ai/tracers/litellm/chat.py
scope3ai/tracers/litellm/instrument.py
scope3ai/tracers/litellm/speech_to_text.py
scope3ai/tracers/litellm/text_to_image.py
scope3ai/tracers/litellm/text_to_speech.py
scope3ai/tracers/mistralai/chat.py
scope3ai/tracers/mistralai/instrument.py
scope3ai/tracers/openai/chat.py
scope3ai/tracers/openai/instrument.py
scope3ai/tracers/openai/speech_to_text.py
scope3ai/tracers/openai/text_to_image.py
scope3ai/tracers/openai/text_to_speech.py
scope3ai/tracers/openai/translation.py
scope3ai/tracers/openai/utils.py
scope3ai/tracers/utils/audio.py
scope3ai/tracers/utils/multimodal.py
scope3ai-0.3.0.dist-info/METADATA
scope3ai-0.3.0.dist-info/WHEEL
scope3ai-0.3.0.dist-info/top_level.txt
scope3ai-0.3.0.dist-info/RECORD
